mdpyformat/__init__.py
mdpyformat/mdf.py
mdpyformat/tocgen.py
mdpyformat-1.0.3.dist-info/LICENSE.txt
mdpyformat-1.0.3.dist-info/METADATA
mdpyformat-1.0.3.dist-info/WHEEL
mdpyformat-1.0.3.dist-info/top_level.txt
mdpyformat-1.0.3.dist-info/RECORD
