Metadata-Version: 2.1
Name: mdpyformat
Version: 1.0.3
Summary: mdformat is a literate programming framework for python.
Home-page: https://github.com/MoserMichael/python-obj-system
Author: Michael Moser
Author-email: moser.michael@gmail.com
License: MIT
Keywords: utility
Platform: UNKNOWN
Classifier: Programming Language :: Python :: 3
Classifier: License :: OSI Approved :: MIT License
Classifier: Operating System :: OS Independent
Classifier: Topic :: Text Processing
Classifier: Topic :: Software Development :: Documentation
Requires-Python: >=3.6
Requires-Dist: subb (==1.0.6)
